LICENSE.txt
MANIFEST.in
README.rst
setup.py
docs/Makefile
docs/changes.rst
docs/cli.rst
docs/conf.py
docs/context.rst
docs/index.rst
docs/step.rst
src/s4u/__init__.py
src/s4u.upgrade.egg-info/PKG-INFO
src/s4u.upgrade.egg-info/SOURCES.txt
src/s4u.upgrade.egg-info/dependency_links.txt
src/s4u.upgrade.egg-info/entry_points.txt
src/s4u.upgrade.egg-info/namespace_packages.txt
src/s4u.upgrade.egg-info/requires.txt
src/s4u.upgrade.egg-info/top_level.txt
src/s4u.upgrade.egg-info/zip-safe
src/s4u/upgrade/__init__.py
src/s4u/upgrade/testing.py
src/s4u/upgrade/tests/__init__.py
src/s4u/upgrade/tests/test_upgrade.py
src/s4u/upgrade/tests/tst-pkg/broken.py
src/s4u/upgrade/tests/tst-pkg/context.py
src/s4u/upgrade/tests/tst-pkg/step.py