Metadata-Version: 1.1
Name: s4u.upgrade
Version: 1.3
Summary: 2Style4You upgrade framework
Home-page: https://readthedocs.org/builds/s4uupgrade/
Author: Simplon B.V. - Wichert Akkerman
Author-email: wichert@wiggy.net
License: BSD
Platform: UNKNOWN
Classifier: Development Status :: 5 - Production/Stable
Classifier: Intended Audience :: Developers
Classifier: License :: OSI Approved :: BSD License
Classifier: Programming Language :: Python :: 2
Classifier: Programming Language :: Python :: 2.6
Classifier: Programming Language :: Python :: 2.7
Classifier: Programming Language :: Python :: 3
Classifier: Programming Language :: Python :: 3.3
Classifier: Programming Language :: Python :: 3.4
Classifier: Topic :: Software Development :: Libraries :: Python Modules
